Metadata-Version: 2.1
Name: pystatusb
Version: 1.2.0
Summary: Control fit-statUSB devices
Home-page: https://github.com/cseelye/pystatusb
Author: Carl Seelye
Author-email: cseelye@gmail.com
License: MIT
Keywords: compulab statusb
Platform: UNKNOWN
License-File: LICENSE
